flightby/__init__.py
flightby/module.py
flightby/byrobot/__init__.py
flightby/byrobot/petrone_v2/__init__.py
flightby/byrobot/petrone_v2/drone.py
flightby/byrobot/petrone_v2/receiver.py
flightby/byrobot/petrone_v2/storage.py
flightby/byrobot/petrone_v2/protocol/__init__.py
flightby/byrobot/petrone_v2/protocol/base.py
flightby/byrobot/petrone_v2/protocol/display.py
flightby/byrobot/petrone_v2/protocol/light.py
flightby/byrobot/petrone_v2/protocol/system.py
flightby/communication/__init__.py
flightby/communication/base.py
flightby/communication/crc.py
flightby-0.1.21.dist-info/DESCRIPTION.rst
flightby-0.1.21.dist-info/METADATA
flightby-0.1.21.dist-info/RECORD
flightby-0.1.21.dist-info/WHEEL
flightby-0.1.21.dist-info/metadata.json
flightby-0.1.21.dist-info/top_level.txt
