Metadata-Version: 2.0
Name: flightby
Version: 0.1.21
Summary: Library for BYROBOT Drone Fighters
Home-page: http://www.byrobot.co.kr
Author: BYROBOT
Author-email: dev@byrobot.co.kr
License: UNKNOWN
Platform: UNKNOWN
